Metadata-Version: 1.1
Name: gds
Version: 0.0.2
Summary: A collection of well known data structures implemented in Python.
Home-page: https://github.com/guidanoli/gds
Author: Guilherme Dantas
Author-email: guidanoli@hotmail.com
License: MIT
Download-URL: https://github.com/guidanoli/gds/archive/0.0.2.tar.gz
Keywords: data structures,graph
Platform: UNKNOWN
Classifier: Development Status :: 3 - Alpha
Classifier: Intended Audience :: Developers
Classifier: License :: OSI Approved :: MIT License
Classifier: Programming Language :: Python :: 3
Classifier: Programming Language :: Python :: 3.5
Classifier: Programming Language :: Python :: 3.6
Classifier: Programming Language :: Python :: 3.7
Classifier: Programming Language :: Python :: 3.8
